[
  {
    "id": "01",
    "title": "2022 회고록",
    "subTitle": "2022년 성장 스토리!",
    "createDate": "2022-12-31",
    "tag": "story",
    "backgroundImage": "https://picsum.photos/200"
  },
  {
    "id": "02",
    "title": "GraphQL을 알아보자",
    "subTitle": "Let's deep in to GraphQL",
    "createDate": "2023-01-15",
    "tag": "tech",
    "backgroundImage": "https://picsum.photos/200"
  },
  {
    "id": "03",
    "title": "zustand",
    "subTitle": "상태관리 알아보기",
    "createDate": "2023-02-20",
    "tag": "frontend",
    "backgroundImage": "https://picsum.photos/200"
  },
  {
    "id": "04",
    "title": "Next.js",
    "subTitle": "풀스택이 되어보자",
    "createDate": "2022-03-24",
    "tag": "fullstack",
    "backgroundImage": "https://picsum.photos/200"
  },
  {
    "id": "05",
    "title": "Docker",
    "subTitle": "study Docker with Mac",
    "createDate": "2023-01-30",
    "tag": "tech",
    "backgroundImage": "https://picsum.photos/200"
  },
  {
    "id": "06",
    "title": "React18 Suspense",
    "subTitle": "how to use Suspense?",
    "createDate": "2023-04-01",
    "tag": "frontend",
    "backgroundImage": "https://picsum.photos/200"
  }
]
